__version__.py
git_versioner-7.1.dist-info/LICENSE
git_versioner-7.1.dist-info/METADATA
git_versioner-7.1.dist-info/WHEEL
git_versioner-7.1.dist-info/entry_points.txt
git_versioner-7.1.dist-info/top_level.txt
git_versioner-7.1.dist-info/RECORD
