Metadata-Version: 2.1
Name: git-versioner
Version: 7.1
Summary: Manage current / next version for project
Author-email: Andrew Leech <andrew@alelec.net>
License: MIT License
Project-URL: Homepage, https://gitlab.com/alelec/__version__
Project-URL: Documentation, https://gitlab.com/alelec/__version__/-/blob/main/README.md
Project-URL: Repository, https://gitlab.com/alelec/__version__
Project-URL: Changelog, https://gitlab.com/alelec/__version__/-/commits/main?ref_type=heads
Requires-Python: >=3.8
License-File: LICENSE
Requires-Dist: setuptools >=57
Requires-Dist: tomli ; python_version < "3.11"
